LICENSE
MANIFEST.in
README.md
README.zh-CN.md
config.example.ini
requirements.txt
setup.py
cp2trans/__init__.py
cp2trans/config.ini
cp2trans/cp2trans.py
cp2trans.egg-info/PKG-INFO
cp2trans.egg-info/SOURCES.txt
cp2trans.egg-info/dependency_links.txt
cp2trans.egg-info/entry_points.txt
cp2trans.egg-info/requires.txt
cp2trans.egg-info/top_level.txt
cp2trans/lang/en.yml
cp2trans/lang/zh-CN.yml