Metadata-Version: 2.1
Name: cp2trans
Version: 1.0.7
Summary: Clipboard to translate.
Home-page: https://github.com/EnderQIU/cp2translate
Author: EnderQIU
Author-email: a934560824@gmail.com
License: GPLv3
Keywords: clipboard translate
Platform: UNKNOWN
Classifier: Development Status :: 4 - Beta
Classifier: Operating System :: Microsoft :: Windows :: Windows 10
Classifier: Intended Audience :: End Users/Desktop
Classifier: License :: OSI Approved :: GNU General Public License v3 (GPLv3)
Classifier: Programming Language :: Python :: 3.6
Classifier: Programming Language :: Python :: 3.7
Classifier: Topic :: Utilities
